sbol2build/__init__.py
sbol2build/abstract_translator.py
sbol2build/constants.py
sbol2build/robotutils.py
sbol2build/sbol2build.py
sbol2build-0.0b3.dist-info/licenses/LICENSE
sbol2build-0.0b3.dist-info/METADATA
sbol2build-0.0b3.dist-info/WHEEL
sbol2build-0.0b3.dist-info/top_level.txt
sbol2build-0.0b3.dist-info/RECORD
